Workbook

Sheet Raw_Data
A1: Order_ID | B1: Order_Date | C1: Customer | D1: City | E1: Product | F1: Category | G1: Quantity | H1: Unit_Price | I1: Sales_Rep | J1: Payment_Status
A2: ORD-1001 | B2: 2026-01-04 | C2: Aisha Khan | D2: Nashik | E2: Laptop | F2: Electronics | G2: 1 | H2: 55000 | I2: R. Patil | J2: Paid
A3: ORD-1002 | B3: 2026-01-05 | C3: Rahul Patil | D3: PUNE | E3: Mouse | F3: Accessories | G3: 3 | H3: 650 | I3: S. More | J3: Paid
A4: ORD-1003 | B4: 2026-01-07 | C4: Zoya Shaikh | D4: Mumbai | E4: Keyboard | F4: Accessories | G4: 2 | H4: 1200 | I4: R. Patil | J4: Pending
A5: ORD-1004 | B5: 2026-01-08 | C5: Aman Joshi | D5: Nashik | E5: Monitor | F5: Electronics | G5: 2 | H5: 12500 | I5: N. Shah | J5: Paid
A6: ORD-1005 | B6: 2026-01-10 | C6: Neha Deshmukh | D6: Pune | E6: Laptop | F6: Electronics | G6: 1 | H6: 55000 | I6: S. More | J6: Paid
A7: ORD-1006 | B7: 2026-01-11 | C7: Kabir More | D7: Mumbai | E7: USB Cable | F7: Accessories | G7: 5 | H7: 250 | I7: N. Shah | J7: Pending
A8: ORD-1007 | B8: 2026-01-13 | C8: Sara Shaikh | D8: Nashik | E8: Webcam | F8: Accessories | G8: 2 | H8: 1800 | I8: R. Patil | J8: Paid
A9: ORD-1008 | B9: 2026-01-14 | C9: Ishaan Kulkarni | D9: pune | E9: Monitor | F9: Electronics | G9: 1 | H9: 12500 | I9: S. More | J9: Paid
A10: ORD-1009 | B10: 2026-01-15 | C10: Mira Shah | D10: Mumbai | E10: Laptop | F10: Electronics | G10: 1 | H10: 55000 | I10: N. Shah | J10: Cancelled
A11: ORD-1010 | B11: 2026-01-17 | C11: Dev Nair | D11: Nashik | E11: Keyboard | F11: Accessories | G11: 4 | H11: 1200 | I11: R. Patil | J11: Paid
A12: ORD-1011 | B12: 2026-01-18 | C12: Aisha Khan | D12: Nashik | E12: Laptop | F12: Electronics | G12: 1 | H12: 55000 | I12: R. Patil | J12: Paid
A13: ORD-1012 | B13: 2026-01-20 | C13: Rahul Patil | D13: Pune | E13: USB Cable | F13: Accessories | G13: 4 | H13: 250 | I13: S. More | J13: Paid
... A16: ORD-1015 | B16: 2026-01-25 | C16: Neha Deshmukh | D16: Pune | E16: Webcam | F16: Accessories | G16: 1 | H16: 1800 | I16: S. More | J16: Paid

Sheet Cleaned_Data
A1: Order_ID | B1: Order_Date | C1: Customer_Clean | D1: City_Clean | E1: Product | F1: Category | G1: Quantity | H1: Unit_Price | I1: Sales_Rep | J1: Payment_Status | K1: Revenue | L1: Duplicate_Flag
A2: =Raw_Data!A2 | B2: =DATEVALUE(Raw_Data!B2) | C2: =PROPER(TRIM(Raw_Data!C2)) | D2: =PROPER(TRIM(Raw_Data!D2)) | E2: =Raw_Data!E2 | F2: =Raw_Data!F2 | G2: =Raw_Data!G2 | H2: =Raw_Data!H2 | I2: =Raw_Data!I2 | J2: =Raw_Data!J2 | K2: =G2*H2 | L2: =IF(COUNTIF($A$2:A2,A2)>1,"Duplicate ID","Check")
A3: =Raw_Data!A3 | B3: =DATEVALUE(Raw_Data!B3) | C3: =PROPER(TRIM(Raw_Data!C3)) | D3: =PROPER(TRIM(Raw_Data!D3)) | E3: =Raw_Data!E3 | F3: =Raw_Data!F3 | G3: =Raw_Data!G3 | H3: =Raw_Data!H3 | I3: =Raw_Data!I3 | J3: =Raw_Data!J3 | K3: =G3*H3 | L3: =IF(COUNTIF($A$2:A3,A3)>1,"Duplicate ID","Check")
A4: =Raw_Data!A4 | B4: =DATEVALUE(Raw_Data!B4) | C4: =PROPER(TRIM(Raw_Data!C4)) | D4: =PROPER(TRIM(Raw_Data!D4)) | E4: =Raw_Data!E4 | F4: =Raw_Data!F4 | G4: =Raw_Data!G4 | H4: =Raw_Data!H4 | I4: =Raw_Data!I4 | J4: =Raw_Data!J4 | K4: =G4*H4 | L4: =IF(COUNTIF($A$2:A4,A4)>1,"Duplicate ID","Check")
A5: =Raw_Data!A5 | B5: =DATEVALUE(Raw_Data!B5) | C5: =PROPER(TRIM(Raw_Data!C5)) | D5: =PROPER(TRIM(Raw_Data!D5)) | E5: =Raw_Data!E5 | F5: =Raw_Data!F5 | G5: =Raw_Data!G5 | H5: =Raw_Data!H5 | I5: =Raw_Data!I5 | J5: =Raw_Data!J5 | K5: =G5*H5 | L5: =IF(COUNTIF($A$2:A5,A5)>1,"Duplicate ID","Check")
A6: =Raw_Data!A6 | B6: =DATEVALUE(Raw_Data!B6) | C6: =PROPER(TRIM(Raw_Data!C6)) | D6: =PROPER(TRIM(Raw_Data!D6)) | E6: =Raw_Data!E6 | F6: =Raw_Data!F6 | G6: =Raw_Data!G6 | H6: =Raw_Data!H6 | I6: =Raw_Data!I6 | J6: =Raw_Data!J6 | K6: =G6*H6 | L6: =IF(COUNTIF($A$2:A6,A6)>1,"Duplicate ID","Check")
A7: =Raw_Data!A7 | B7: =DATEVALUE(Raw_Data!B7) | C7: =PROPER(TRIM(Raw_Data!C7)) | D7: =PROPER(TRIM(Raw_Data!D7)) | E7: =Raw_Data!E7 | F7: =Raw_Data!F7 | G7: =Raw_Data!G7 | H7: =Raw_Data!H7 | I7: =Raw_Data!I7 | J7: =Raw_Data!J7 | K7: =G7*H7 | L7: =IF(COUNTIF($A$2:A7,A7)>1,"Duplicate ID","Check")
A8: =Raw_Data!A8 | B8: =DATEVALUE(Raw_Data!B8) | C8: =PROPER(TRIM(Raw_Data!C8)) | D8: =PROPER(TRIM(Raw_Data!D8)) | E8: =Raw_Data!E8 | F8: =Raw_Data!F8 | G8: =Raw_Data!G8 | H8: =Raw_Data!H8 | I8: =Raw_Data!I8 | J8: =Raw_Data!J8 | K8: =G8*H8 | L8: =IF(COUNTIF($A$2:A8,A8)>1,"Duplicate ID","Check")
A9: =Raw_Data!A9 | B9: =DATEVALUE(Raw_Data!B9) | C9: =PROPER(TRIM(Raw_Data!C9)) | D9: =PROPER(TRIM(Raw_Data!D9)) | E9: =Raw_Data!E9 | F9: =Raw_Data!F9 | G9: =Raw_Data!G9 | H9: =Raw_Data!H9 | I9: =Raw_Data!I9 | J9: =Raw_Data!J9 | K9: =G9*H9 | L9: =IF(COUNTIF($A$2:A9,A9)>1,"Duplicate ID","Check")
A10: =Raw_Data!A10 | B10: =DATEVALUE(Raw_Data!B10) | C10: =PROPER(TRIM(Raw_Data!C10)) | D10: =PROPER(TRIM(Raw_Data!D10)) | E10: =Raw_Data!E10 | F10: =Raw_Data!F10 | G10: =Raw_Data!G10 | H10: =Raw_Data!H10 | I10: =Raw_Data!I10 | J10: =Raw_Data!J10 | K10: =G10*H10 | L10: =IF(COUNTIF($A$2:A10,A10)>1,"Duplicate ID","Check")
A11: =Raw_Data!A11 | B11: =DATEVALUE(Raw_Data!B11) | C11: =PROPER(TRIM(Raw_Data!C11)) | D11: =PROPER(TRIM(Raw_Data!D11)) | E11: =Raw_Data!E11 | F11: =Raw_Data!F11 | G11: =Raw_Data!G11 | H11: =Raw_Data!H11 | I11: =Raw_Data!I11 | J11: =Raw_Data!J11 | K11: =G11*H11 | L11: =IF(COUNTIF($A$2:A11,A11)>1,"Duplicate ID","Check")
A12: =Raw_Data!A12 | B12: =DATEVALUE(Raw_Data!B12) | C12: =PROPER(TRIM(Raw_Data!C12)) | D12: =PROPER(TRIM(Raw_Data!D12)) | E12: =Raw_Data!E12 | F12: =Raw_Data!F12 | G12: =Raw_Data!G12 | H12: =Raw_Data!H12 | I12: =Raw_Data!I12 | J12: =Raw_Data!J12 | K12: =G12*H12 | L12: =IF(COUNTIF($A$2:A12,A12)>1,"Duplicate ID","Check")
A13: =Raw_Data!A13 | B13: =DATEVALUE(Raw_Data!B13) | C13: =PROPER(TRIM(Raw_Data!C13)) | D13: =PROPER(TRIM(Raw_Data!D13)) | E13: =Raw_Data!E13 | F13: =Raw_Data!F13 | G13: =Raw_Data!G13 | H13: =Raw_Data!H13 | I13: =Raw_Data!I13 | J13: =Raw_Data!J13 | K13: =G13*H13 | L13: =IF(COUNTIF($A$2:A13,A13)>1,"Duplicate ID","Check")
... A16: =Raw_Data!A16 | B16: =DATEVALUE(Raw_Data!B16) | C16: =PROPER(TRIM(Raw_Data!C16)) | D16: =PROPER(TRIM(Raw_Data!D16)) | E16: =Raw_Data!E16 | F16: =Raw_Data!F16 | G16: =Raw_Data!G16 | H16: =Raw_Data!H16 | I16: =Raw_Data!I16 | J16: =Raw_Data!J16 | K16: =G16*H16 | L16: =IF(COUNTIF($A$2:A16,A16)>1,"Duplicate ID","Check")

Sheet Analysis
A1: Metric | B1: Formula / Result | C1: Interpretation
A2: Total orders | B2: =COUNTA(Cleaned_Data!A2:A16) | C2: Counts order records; duplicate IDs should be reviewed separately.
A3: Total revenue | B3: =SUM(Cleaned_Data!K2:K16) | C3: Revenue = Quantity × Unit Price; includes all payment statuses.
A4: Paid revenue | B4: =SUMIFS(Cleaned_Data!K2:K16,Cleaned_Data!J2:J16,"Paid") | C4: Revenue on paid orders only.
A5: Pending order count | B5: =COUNTIF(Cleaned_Data!J2:J16,"Pending") | C5: Orders awaiting payment.
A6: Cancelled order count | B6: =COUNTIF(Cleaned_Data!J2:J16,"Cancelled") | C6: Cancelled orders.
A7: Average order value | B7: =AVERAGE(Cleaned_Data!K2:K16) | C7: Average revenue per order row.
A8: Electronics revenue | B8: =SUMIF(Cleaned_Data!F2:F16,"Electronics",Cleaned_Data!K2:K16) | C8: Revenue from Electronics category.
A9: Accessories revenue | B9: =SUMIF(Cleaned_Data!F2:F16,"Accessories",Cleaned_Data!K2:K16) | C9: Revenue from Accessories category.
A11: Cleaning Operation | B11: How to do it in Excel | C11: Why it matters
A12: Trim whitespace | B12: =TRIM(A2) | C12: Removes leading/trailing and repeated spaces.
A13: Standardize case | B13: =PROPER(A2) or =UPPER(A2) | C13: Makes categories consistent; choose case style to suit the field.
A14: Remove duplicates | B14: Data > Remove Duplicates | C14: Review the key columns first; do not blindly delete legitimate repeat purchases.
A15: Handle blanks | B15: Filter blanks; decide whether to fill, flag, or remove | C15: Never assume a blank means zero.
A16: Convert text dates | B16: Data > Text to Columns or DATEVALUE | C16: Confirm locale/date format to avoid swapping day and month.
A17: Validate categories | B17: Data > Data Validation > List | C17: Restricts statuses to approved values.
A18: Calculate derived field | B18: Quantity * Unit Price | C18: Makes transformations repeatable and auditable.
